dora_lakehouse/__init__.py
dora_lakehouse/catalog.py
dora_lakehouse/context.py
dora_lakehouse/datatable.py
dora_lakehouse/utils.py
dora_lakehouse-0.0.14.dist-info/LICENSE
dora_lakehouse-0.0.14.dist-info/WHEEL
dora_lakehouse-0.0.14.dist-info/METADATA
dora_lakehouse-0.0.14.dist-info/RECORD
