Metadata-Version: 2.1
Name: dora-lakehouse
Version: 0.0.14
Summary: Dora Lakehouse
Home-page: https://github.com/doraproject/lakehouse
License: Apache-2.0
Keywords: dora,lakehouse
Author: Didone
Author-email: didone@live.com
Maintainer: DataLabs
Maintainer-email: time.dataanalytics.datalabs@compasso.com.br
Requires-Python: >=3.6,<4.0
Classifier: Development Status :: 4 - Beta
Classifier: License :: OSI Approved :: Apache Software License
Classifier: Programming Language :: Python :: 3
Classifier: Programming Language :: Python :: 3.10
Classifier: Programming Language :: Python :: 3.6
Classifier: Programming Language :: Python :: 3.7
Classifier: Programming Language :: Python :: 3.8
Classifier: Programming Language :: Python :: 3.9
Classifier: Topic :: Software Development :: Libraries
Classifier: Topic :: Software Development :: Libraries :: Python Modules
Project-URL: Bug Tracker, https://github.com/doraproject/lakehouse/issues
Project-URL: Repository, https://github.com/doraproject/lakehouse.git
